parserXBRL/__init__.py
parserXBRL/parse_xbrl_ifrs.py
parserXBRL/parser_xbrl.py
parserXBRL/setup.py
parserXBRL/cargar_fichero/__init__.py
parserXBRL/cargar_fichero/cargar.py
parserXBRL/taxonomia/__init__.py
parserXBRL/taxonomia/instancia/XbrlElement.py
parserXBRL/taxonomia/instancia/XbrlIntancia.py
parserXBRL/taxonomia/instancia/__init__.py
parserXBRL/taxonomia/linkbase/Arc.py
parserXBRL/taxonomia/linkbase/Label.py
parserXBRL/taxonomia/linkbase/Locator.py
parserXBRL/taxonomia/linkbase/__init__.py
parserXBRL/utils/TaxonomiaRe.py
parserXBRL/utils/__init__.py
parserXBRL/utils/ns.py
draco_parse-0.4.dist-info/METADATA
draco_parse-0.4.dist-info/WHEEL
draco_parse-0.4.dist-info/top_level.txt
draco_parse-0.4.dist-info/RECORD
